worldview_config/__init__.py
worldview_config/_version.py
worldview_config/cli.py
worldview_config/merge.py
worldview_config/models.py
worldview_config/render.py
worldview_config/templates/discipline.json.jinja
worldview_config/templates/layer.json.jinja
worldview_config/templates/layer.md.jinja
worldview_config/templates/layerOrder.json.jinja
worldview_config/templates/measurement.json.jinja
worldview_config-0.2.1.dist-info/METADATA
worldview_config-0.2.1.dist-info/WHEEL
worldview_config-0.2.1.dist-info/entry_points.txt
worldview_config-0.2.1.dist-info/licenses/LICENSE.txt
worldview_config-0.2.1.dist-info/RECORD
